tftrainer/__init__.py
tftrainer/optimizer.py
tftrainer/trainarguments.py
tftrainer/trainer.py
TFTrainer-0.2.2.dist-info/METADATA
TFTrainer-0.2.2.dist-info/WHEEL
TFTrainer-0.2.2.dist-info/top_level.txt
TFTrainer-0.2.2.dist-info/RECORD
